pyolan/__init__.py
pyolan/drawing.py
pyolan/figure_parser.py
pyolan/parser.py
pyolan/primitives.py
pyolan/py.typed
pyolan/rolls.py
pyolan-0.1.0.dist-info/METADATA
pyolan-0.1.0.dist-info/WHEEL
pyolan-0.1.0.dist-info/RECORD
