Metadata-Version: 2.4
Name: pyolan
Version: 0.1.0
Summary: One Letter Aerobatic Notation Parser
Author-email: Thomas David <thomasdavid0@gmail.com>
Requires-Python: >=3.13
Requires-Dist: flightanalysis
Requires-Dist: flightdata
Requires-Dist: pfc-geometry
Requires-Dist: pfcschemas>=0.1.10
Requires-Dist: pydantic>=2.9.2
